setup.py
python_wd_parallel.egg-info/PKG-INFO
python_wd_parallel.egg-info/SOURCES.txt
python_wd_parallel.egg-info/dependency_links.txt
python_wd_parallel.egg-info/requires.txt
python_wd_parallel.egg-info/top_level.txt
wd/__init__.py
wd/parallel.py