Metadata-Version: 1.0
Name: python-wd-parallel
Version: 0.0.3
Summary: python-wd-parallel lets you easilly run your test in multiple borwsers.
Home-page: https://github.com/OniOni
Author: Mathieu Sabourin
Author-email: mathieu.c.sabourin@gmail.com
License: UNKNOWN
Download-URL: https://github.com/OniOni/python-parallel-wd
Keywords: Testing,Selenium
Platform: UNKNOWN
Classifier: Development Status :: 3 - Alpha
Classifier: Environment :: No Input/Output (Daemon)
Classifier: Intended Audience :: Developers
Classifier: License :: OSI Approved :: Apache Software License
Classifier: Natural Language :: English
Classifier: Operating System :: POSIX
Classifier: Programming Language :: Python :: 2.7
Classifier: Programming Language :: Python :: Implementation :: CPython
Classifier: Topic :: Software Development :: Libraries
Classifier: Topic :: Software Development :: Quality Assurance
Classifier: Topic :: Software Development :: Testing
